b_aws_testing_framework/__init__.py
b_aws_testing_framework/base_testing_manager.py
b_aws_testing_framework/credentials.py
b_aws_testing_framework/tools/__init__.py
b_aws_testing_framework/tools/cdk_testing/__init__.py
b_aws_testing_framework/tools/cdk_testing/cdk_tool_config.py
b_aws_testing_framework/tools/cdk_testing/testing_manager.py
b_aws_testing_framework/tools/cdk_testing/testing_stack.py
b_aws_testing_framework/tools/cf_testing/__init__.py
b_aws_testing_framework/tools/cf_testing/cf_tool_config.py
b_aws_testing_framework/tools/cf_testing/stack_waiter.py
b_aws_testing_framework/tools/cf_testing/testing_manager.py
b_aws_testing_framework_test/tools/__init__.py
b_aws_testing_framework_test/tools/testing_with_cdk/__init__.py
b_aws_testing_framework_test/tools/testing_with_cdk/app.py
b_aws_testing_framework_test/tools/testing_with_cdk/conftest.py
b_aws_testing_framework_test/tools/testing_with_cdk/infrastructure.py
b_aws_testing_framework_test/tools/testing_with_cdk/tests/__init__.py
b_aws_testing_framework_test/tools/testing_with_cdk/tests/test_outputs.py
b_aws_testing_framework_test/tools/testing_with_cdk/tests/test_stack_exists.py
b_aws_testing_framework_test/tools/testing_with_cf/__init__.py
b_aws_testing_framework_test/tools/testing_with_cf/conftest.py
b_aws_testing_framework_test/tools/testing_with_cf/tests/__init__.py
b_aws_testing_framework_test/tools/testing_with_cf/tests/test_stack_exists.py
b_aws_testing_framework-1.0.1.dist-info/LICENSE
b_aws_testing_framework-1.0.1.dist-info/METADATA
b_aws_testing_framework-1.0.1.dist-info/WHEEL
b_aws_testing_framework-1.0.1.dist-info/top_level.txt
b_aws_testing_framework-1.0.1.dist-info/RECORD
