Metadata-Version: 2.1
Name: b-aws-testing-framework
Version: 1.0.1
Summary: AWS infrastructure testing framework that supports multiple IAC tools.
Home-page: https://github.com/biomapas/B.AwsTestingFramework.git
Author: Laimonas Sutkus
Author-email: laimonas.sutkus@biomapas.com
License: Apache License 2.0
Keywords: AWS Test IAC
Classifier: Programming Language :: Python :: 3
Classifier: Operating System :: OS Independent
License-File: LICENSE
Requires-Dist: aws-cdk-lib (<3.0.0,>=2.0.0)
Requires-Dist: aws-cdk-constructs (<3.0.0,>=2.0.0)
Requires-Dist: boto3 (<2.0.0,>=1.16.0)
Requires-Dist: pytest (<7.0.0,>=6.0.2)
Requires-Dist: b-continuous-subprocess (<1.0.0,>=0.3.2)
Requires-Dist: b-cf-outputs (<1.0.0,>=0.0.3)
